odoo/addons/l10n_fr_account_payment_intl_credit_transfer/README.rst
odoo/addons/l10n_fr_account_payment_intl_credit_transfer/__init__.py
odoo/addons/l10n_fr_account_payment_intl_credit_transfer/__manifest__.py
odoo/addons/l10n_fr_account_payment_intl_credit_transfer/data/account_pain_regulatory_reporting.xml
odoo/addons/l10n_fr_account_payment_intl_credit_transfer/i18n/l10n_fr_account_payment_intl_credit_transfer.pot
odoo/addons/l10n_fr_account_payment_intl_credit_transfer/models/__init__.py
odoo/addons/l10n_fr_account_payment_intl_credit_transfer/models/account_payment_line.py
odoo/addons/l10n_fr_account_payment_intl_credit_transfer/models/res_partner.py
odoo/addons/l10n_fr_account_payment_intl_credit_transfer/readme/CONTRIBUTORS.md
odoo/addons/l10n_fr_account_payment_intl_credit_transfer/readme/DESCRIPTION.md
odoo/addons/l10n_fr_account_payment_intl_credit_transfer/static/description/icon.png
odoo/addons/l10n_fr_account_payment_intl_credit_transfer/static/description/index.html
odoo/addons/l10n_fr_account_payment_intl_credit_transfer/views/res_partner.xml
odoo_addon_l10n_fr_account_payment_intl_credit_transfer-19.0.1.0.0.2.dist-info/METADATA
odoo_addon_l10n_fr_account_payment_intl_credit_transfer-19.0.1.0.0.2.dist-info/WHEEL
odoo_addon_l10n_fr_account_payment_intl_credit_transfer-19.0.1.0.0.2.dist-info/top_level.txt
odoo_addon_l10n_fr_account_payment_intl_credit_transfer-19.0.1.0.0.2.dist-info/RECORD
