Metadata-Version: 2.1
Name: odoo-addon-l10n_fr_account_payment_intl_credit_transfer
Version: 19.0.1.0.0.2
Requires-Dist: odoo-addon-account_payment_sepa_base==19.0.*
Requires-Dist: odoo==19.0.*
Summary: Regulatory reporting codes for ISO 20022 credit transfer files
Home-page: https://github.com/OCA/l10n-france
License: AGPL-3
Author: Akretion,Odoo Community Association (OCA)
Author-email: support@odoo-community.org
Classifier: Programming Language :: Python
Classifier: Framework :: Odoo
Classifier: Framework :: Odoo :: 19.0
Classifier: License :: OSI Approved :: GNU Affero General Public License v3
